{"cameraMode":{"drawMode":0,"name":"Shaded","section":"Shading Mode"},"sceneLighting":true,"audioPlay":false,"sceneViewState":{"m_AlwaysRefresh":false,"showFog":true,"showSkybox":true,"showFlares":true,"showImageEffects":true,"showParticleSystems":true,"showVisualEffectGraphs":true,"m_FxEnabled":true},"in2DMode":false,"pivot":{"x":0.0,"y":0.0,"z":0.0},"rotation":{"x":-0.050093431025743487,"y":0.9498886466026306,"z":-0.21471858024597169,"w":-0.221607968211174},"size":12.954080581665039,"orthographic":false}